docs/scripts/gen_pages.py
examples/bilateral_symmetry.py
examples/contraction_expansion.py
examples/equilibrium.py
examples/smoothness.py
examples/synchronization.py
examples/tsv_reader.py
pyeyesweb/__init__.py
pyeyesweb/analysis_primitives/__init__.py
pyeyesweb/analysis_primitives/bilateral_symmetry.py
pyeyesweb/analysis_primitives/synchronization.py
pyeyesweb/data_models/__init__.py
pyeyesweb/data_models/sliding_window.py
pyeyesweb/data_models/thread_safe_buffer.py
pyeyesweb/low_level/__init__.py
pyeyesweb/low_level/contraction_expansion.py
pyeyesweb/low_level/equilibrium.py
pyeyesweb/low_level/smoothness.py
pyeyesweb/mid_level/__init__.py
pyeyesweb/utils/__init__.py
pyeyesweb/utils/math_utils.py
pyeyesweb/utils/signal_generators.py
pyeyesweb/utils/signal_processing.py
pyeyesweb/utils/tsv_reader.py
pyeyesweb/utils/validators.py
pyeyesweb-0.0.1a5.dist-info/licenses/.github/LICENSE
tests/__init__.py
tests/conftest.py
tests/feature_test_cli.py
tests/test_helpers/__init__.py
tests/test_helpers/base_tester.py
tests/test_helpers/cli_formatting.py
tests/test_helpers/thresholds.py
tests/unit/__init__.py
tests/unit/test_complete.py
pyeyesweb-0.0.1a5.dist-info/METADATA
pyeyesweb-0.0.1a5.dist-info/WHEEL
pyeyesweb-0.0.1a5.dist-info/top_level.txt
pyeyesweb-0.0.1a5.dist-info/RECORD
