Metadata-Version: 2.4
Name: pyeyesweb
Version: 0.0.1a5
Summary: PyEyesWeb is a research toolkit for extracting quantitative features from human movement data.
Author-email: InfoMus Lab - Casa Paganini <cp.infomus@gmail.com>
Maintainer-email: Nicola Corbellini <nicola.corbellini@edu.unige.it>, Gabriele Romano <gabriele.romano@edu.unige.it>, Sanket Rajeev Sabharwal <sabharwal@edu.unige.it>, Simone Ghisio <simoneghisio@gmail.com>, Paolo Coletta <paolocoletta@gmail.com>
License-Expression: MIT
Project-URL: Documentation, https://infomuscp.github.io/PyEyesWeb/
Project-URL: Casa Paganini, http://www.casapaganini.org/index_eng.php
Project-URL: Resilence EU Project, https://resilence.eu/
Keywords: movement analysis,human movement,motor control,biomechanics,kinematics,time series,synchronization,computational movement,quantitative movement
Classifier: Intended Audience :: Science/Research
Classifier: Intended Audience :: Education
Classifier: Topic :: Scientific/Engineering
Classifier: Topic :: Scientific/Engineering :: Artificial Intelligence
Classifier: Topic :: Scientific/Engineering :: Information Analysis
Classifier: Topic :: Scientific/Engineering :: Human Machine Interfaces
Classifier: Programming Language :: Python :: 3
Classifier: Programming Language :: Python :: 3.9
Classifier: Programming Language :: Python :: 3.10
Classifier: Programming Language :: Python :: 3.11
Classifier: Programming Language :: Python :: 3.12
Classifier: Operating System :: OS Independent
Requires-Python: >=3.8
License-File: .github/LICENSE
Requires-Dist: numpy<2
Requires-Dist: scipy<=1.16.2
Requires-Dist: numba>=0.57.0
Requires-Dist: scikit-learn>=1.3.0
Provides-Extra: dev
Requires-Dist: build==1.3.0; extra == "dev"
Requires-Dist: mediapipe==0.10.21; extra == "dev"
Requires-Dist: opencv-python>=4.8.0; extra == "dev"
Requires-Dist: matplotlib>=3.7.0; extra == "dev"
Requires-Dist: pytest>=8.0.0; extra == "dev"
Requires-Dist: pytest-cov>=4.0.0; extra == "dev"
Requires-Dist: setuptools==78.1.1; extra == "dev"
Requires-Dist: wheel==0.45.1; extra == "dev"
Requires-Dist: mkdocs==1.6.1; extra == "dev"
Requires-Dist: mkdocs-material==9.6.20; extra == "dev"
Requires-Dist: mkdocstrings==0.30.1; extra == "dev"
Requires-Dist: mkdocstrings-python==1.18.2; extra == "dev"
Requires-Dist: mkdocs-gen-files==0.5.0; extra == "dev"
Requires-Dist: mkdocs-literate-nav==0.6.2; extra == "dev"
Requires-Dist: mkdocs-section-index==0.3.10; extra == "dev"
Provides-Extra: touchdesigner
Requires-Dist: numpy==1.24.1; extra == "touchdesigner"
Dynamic: license-file
